maildump/__init__.py
maildump/db.py
maildump/smtp.py
maildump/util.py
maildump/web.py
maildump/web_realtime.py
maildump/static/css/maildump.scss
maildump/static/css/reset.css
maildump/static/dist/.keep
maildump/static/dist/icon_16x16.3ac2402b.png
maildump/static/dist/icon_32x32.20bcb926.png
maildump/static/dist/maildump.8315b07f.css
maildump/static/dist/maildump.8315b07f.css.map
maildump/static/dist/maildump.b6a54245.js
maildump/static/dist/maildump.b6a54245.js.map
maildump/static/images/icon_16x16.png
maildump/static/images/icon_32x32.png
maildump/static/images/icon_80x80.png
maildump/static/js/jquery-stub.js
maildump/static/js/maildump.js
maildump/static/js/message.js
maildump/static/js/util.js
maildump/templates/index.html
maildump/templates/index.parcel.html
maildump/vendor/__init__.py
maildump/vendor/smtpd.py
maildump_runner/__init__.py
maildump_runner/geventdaemon.py
maildump_runner/main.py
maildump-1.1.dist-info/LICENSE
maildump-1.1.dist-info/METADATA
maildump-1.1.dist-info/WHEEL
maildump-1.1.dist-info/entry_points.txt
maildump-1.1.dist-info/top_level.txt
maildump-1.1.dist-info/RECORD
