Metadata-Version: 2.1
Name: maildump
Version: 1.1
Summary: An SMTP server that makes all received mails accessible via a web interface and REST API.
Home-page: https://github.com/ThiefMaster/maildump
Download-URL: https://github.com/ThiefMaster/maildump
Author: Adrian Mönnich
Author-email: adrian@planetcoding.net
License: MIT
Classifier: Development Status :: 4 - Beta
Classifier: Programming Language :: Python
Classifier: Programming Language :: Python :: 3.12
Classifier: Environment :: No Input/Output (Daemon)
Classifier: Environment :: Web Environment
Classifier: Intended Audience :: Developers
Classifier: Intended Audience :: System Administrators
Classifier: License :: OSI Approved :: MIT License
Classifier: Topic :: Communications :: Email
Classifier: Topic :: Software Development
Classifier: Topic :: System :: Networking
Classifier: Topic :: Utilities
Requires-Python: >=3.12
License-File: LICENSE
Requires-Dist: beautifulsoup4
Requires-Dist: Flask
Requires-Dist: gevent
Requires-Dist: html5lib
Requires-Dist: lockfile
Requires-Dist: Logbook
Requires-Dist: passlib
Requires-Dist: pyasynchat
Requires-Dist: pyasyncore
Requires-Dist: python-daemon
Requires-Dist: pytz
Provides-Extra: dev
Requires-Dist: ruff ; extra == 'dev'
Requires-Dist: twine ; extra == 'dev'
Requires-Dist: wheel ; extra == 'dev'
